python_sb/__init__.py
python_sb-0.0.1.dist-info/METADATA
python_sb-0.0.1.dist-info/WHEEL
python_sb-0.0.1.dist-info/entry_points.txt
python_sb-0.0.1.dist-info/RECORD
